gray_box_clf/__init__.py
gray_box_clf/classification_functions.py
gray_box_clf/data_reprocessing.py
gray_box_clf/semi_supervised.py
gray_box_clf/supervised_models.py
gray_box_clf/unsupervised_models.py
gray_box_clf-0.3.6.dist-info/LICENSE.txt
gray_box_clf-0.3.6.dist-info/METADATA
gray_box_clf-0.3.6.dist-info/WHEEL
gray_box_clf-0.3.6.dist-info/top_level.txt
gray_box_clf-0.3.6.dist-info/RECORD
