Metadata-Version: 2.1
Name: gray-box-clf
Version: 0.3.6
Summary: classificaion witout wax
Home-page: https://github.com/AdamHamody/sincera_gray_box
Author: Adam H. Agbaria
Author-email: adam.h.agb@gmail.com
License: MIT
Download-URL: https://github.com/AdamHamody/sincera_gray_box/archive/0.0.1.tar.gz
Keywords: chi2,classification
Platform: UNKNOWN
Classifier: Development Status :: 3 - Alpha
Classifier: Intended Audience :: Developers
Classifier: Topic :: Software Development :: Build Tools
Classifier: License :: OSI Approved :: MIT License
Classifier: Programming Language :: Python :: 3
Classifier: Programming Language :: Python :: 3.4
Classifier: Programming Language :: Python :: 3.5
Classifier: Programming Language :: Python :: 3.6
Requires-Dist: matplotlib
Requires-Dist: scipy
Requires-Dist: numpy
Requires-Dist: pandas
Requires-Dist: pyod
Requires-Dist: sklearn
